Metadata-Version: 2.1
Name: fucking-read
Version: 0.1.2
Summary: Used exnd-curses to output file content.
Home-page: https://github.com/shantanu-kor/fread.git
Author: Shantanu Kor
Author-email: kor.shantanu1@gmail.com
Classifier: Programming Language :: Python :: 3
Classifier: License :: OSI Approved :: MIT License
Classifier: Operating System :: OS Independent
Requires-Python: >=3.6
License-File: LICENSE
Requires-Dist: exnd-curses
